pybarcoder/__init__.py
pybarcoder/builder.py
pybarcoder/msyh.ttf.py
pybarcoder-0.9.1.dist-info/LICENSE
pybarcoder-0.9.1.dist-info/METADATA
pybarcoder-0.9.1.dist-info/WHEEL
pybarcoder-0.9.1.dist-info/top_level.txt
pybarcoder-0.9.1.dist-info/RECORD
