Metadata-Version: 2.1
Name: pybarcoder
Version: 0.9.1
Summary: pybarcoder base on python-barcode
Home-page: https://github.com/sunglowrise/pybarcoder
Maintainer: Murray
Maintainer-email: sunglowrise@qq.com
License: MIT
Download-URL: https://github.com/sunglowrise/pybarcoder
Keywords: barcode barCoder
Platform: Platform Independent
Classifier: Intended Audience :: Developers
Classifier: Topic :: Software Development :: Libraries :: Python Modules
Classifier: Topic :: Internet :: WWW/HTTP :: Dynamic Content :: CGI Tools/Libraries
Classifier: Programming Language :: Python :: 3.6
Requires-Python: >=3.5
Requires-Dist: python-barcode (==0.11.0)
Requires-Dist: pillow (>=7.1.2)
